pyplatform/datalake/__init__.py
pyplatform/datalake/datalake.py
pyplatform_datalake-2020.12.1.dist-info/METADATA
pyplatform_datalake-2020.12.1.dist-info/WHEEL
pyplatform_datalake-2020.12.1.dist-info/top_level.txt
pyplatform_datalake-2020.12.1.dist-info/RECORD
