Metadata-Version: 2.1
Name: pyplatform-datalake
Version: 2020.12.1
Summary: Pyplatform-datalake package provides functions for Google Cloud Storage and Microsoft Storage services.
Home-page: https://github.com/mhadi813/pyplatform
Author: Muhammad Hadi
Author-email: mhadi813@gmail.com
License: BSD
Keywords: google bigquery cloud functions storage jupyterlab python SQL
Platform: UNKNOWN
Classifier: Development Status :: 4 - Beta
Classifier: Intended Audience :: Developers
Classifier: Topic :: Office/Business
Classifier: License :: OSI Approved :: BSD License
Classifier: Programming Language :: Python :: 3.6
Classifier: Programming Language :: Python :: 3.7
Classifier: Programming Language :: Python :: 3.8
Requires-Dist: google-cloud-storage (==1.31.0)
Requires-Dist: gcsfs (==0.7.0)
Requires-Dist: azure-storage-blob (==1.5.0)
Requires-Dist: xlrd (==1.2.0)
Requires-Dist: XlsxWriter (==1.3.3)
Requires-Dist: openpyxl (==3.0.3)
Requires-Dist: fsspec (==0.8.0)
Requires-Dist: pyplatform-common
